maguniverse/__init__.py
maguniverse/data/__init__.py
maguniverse/data/gas/__init__.py
maguniverse/data/gas/jijina1999.py
maguniverse/data/gas/sources.py
maguniverse/data/polarization/__init__.py
maguniverse/data/polarization/dotson2010.py
maguniverse/data/polarization/harris2018.py
maguniverse/data/polarization/matthews2009.py
maguniverse/data/polarization/sources.py
maguniverse/data/zeeman/__init__.py
maguniverse/data/zeeman/crutcher2010.py
maguniverse/data/zeeman/sources.py
maguniverse/service/__init__.py
maguniverse/service/get.py
maguniverse/utils/__init__.py
maguniverse/utils/docs_out.py
maguniverse/utils/fetch_ascii.py
maguniverse/utils/generate_manifest.py
maguniverse-0.1.4.dist-info/licenses/LICENSE
maguniverse-0.1.4.dist-info/METADATA
maguniverse-0.1.4.dist-info/WHEEL
maguniverse-0.1.4.dist-info/top_level.txt
maguniverse-0.1.4.dist-info/RECORD
