Metadata-Version: 2.4
Name: maguniverse
Version: 0.1.4
Summary: A Python-based data manager for working with tabulated data from publications of observational surveys of cosmic magnetic fields.
Home-page: https://github.com/xli2522/maguniverse
Author: X. Li
Classifier: Programming Language :: Python :: 3
Classifier: License :: OSI Approved :: MIT License
Classifier: Operating System :: OS Independent
Requires-Python: >=3.6
License-File: LICENSE
Requires-Dist: requests
Requires-Dist: pandas
Requires-Dist: jinja2
Dynamic: author
Dynamic: classifier
Dynamic: description
Dynamic: description-content-type
Dynamic: home-page
Dynamic: license-file
Dynamic: requires-dist
Dynamic: requires-python
Dynamic: summary
